{
  "store_id": "1085",
  "store_slug": "lachenaie-terrebonne-qc-1085",
  "results": [
    {
      "sku": "6000208418990",
      "status": "not_found",
      "store_id": "1085",
      "store_slug": "lachenaie-terrebonne-qc-1085",
      "checked_at": "2026-02-12T04:15:55Z"
    },
    {
      "sku": "6000201209824",
      "status": "not_found",
      "store_id": "1085",
      "store_slug": "lachenaie-terrebonne-qc-1085",
      "checked_at": "2026-02-12T04:15:57Z"
    },
    {
      "sku": "6000196093848",
      "status": "not_found",
      "store_id": "1085",
      "store_slug": "lachenaie-terrebonne-qc-1085",
      "checked_at": "2026-02-12T04:15:58Z"
    },
    {
      "sku": "6000201874801",
      "status": "not_found",
      "store_id": "1085",
      "store_slug": "lachenaie-terrebonne-qc-1085",
      "checked_at": "2026-02-12T04:16:00Z"
    },
    {
      "sku": "6000202420426",
      "status": "not_found",
      "store_id": "1085",
      "store_slug": "lachenaie-terrebonne-qc-1085",
      "checked_at": "2026-02-12T04:16:02Z"
    },
    {
      "sku": "114077",
      "status": "not_found",
      "store_id": "1085",
      "store_slug": "lachenaie-terrebonne-qc-1085",
      "checked_at": "2026-02-12T04:16:04Z"
    },
    {
      "sku": "6000207661987",
      "status": "not_found",
      "store_id": "1085",
      "store_slug": "lachenaie-terrebonne-qc-1085",
      "checked_at": "2026-02-12T04:16:05Z"
    },
    {
      "sku": "6000198726314",
      "status": "not_found",
      "store_id": "1085",
      "store_slug": "lachenaie-terrebonne-qc-1085",
      "checked_at": "2026-02-12T04:16:07Z"
    },
    {
      "sku": "6000204768209",
      "status": "not_found",
      "store_id": "1085",
      "store_slug": "lachenaie-terrebonne-qc-1085",
      "checked_at": "2026-02-12T04:16:08Z"
    },
    {
      "sku": "6000199891127",
      "status": "not_found",
      "store_id": "1085",
      "store_slug": "lachenaie-terrebonne-qc-1085",
      "checked_at": "2026-02-12T04:16:10Z"
    },
    {
      "sku": "6000207877900",
      "status": "not_found",
      "store_id": "1085",
      "store_slug": "lachenaie-terrebonne-qc-1085",
      "checked_at": "2026-02-12T04:16:12Z"
    },
    {
      "sku": "6000203265250",
      "status": "not_found",
      "store_id": "1085",
      "store_slug": "lachenaie-terrebonne-qc-1085",
      "checked_at": "2026-02-12T04:16:13Z"
    },
    {
      "sku": "6000198700959",
      "status": "not_found",
      "store_id": "1085",
      "store_slug": "lachenaie-terrebonne-qc-1085",
      "checked_at": "2026-02-12T04:16:15Z"
    },
    {
      "sku": "6000208073112",
      "status": "not_found",
      "store_id": "1085",
      "store_slug": "lachenaie-terrebonne-qc-1085",
      "checked_at": "2026-02-12T04:16:17Z"
    },
    {
      "sku": "6000208073625",
      "status": "not_found",
      "store_id": "1085",
      "store_slug": "lachenaie-terrebonne-qc-1085",
      "checked_at": "2026-02-12T04:16:18Z"
    },
    {
      "sku": "6000201204931",
      "status": "not_found",
      "store_id": "1085",
      "store_slug": "lachenaie-terrebonne-qc-1085",
      "checked_at": "2026-02-12T04:16:20Z"
    },
    {
      "sku": "6000204264313",
      "status": "not_found",
      "store_id": "1085",
      "store_slug": "lachenaie-terrebonne-qc-1085",
      "checked_at": "2026-02-12T04:16:22Z"
    },
    {
      "sku": "6000208073118",
      "status": "not_found",
      "store_id": "1085",
      "store_slug": "lachenaie-terrebonne-qc-1085",
      "checked_at": "2026-02-12T04:16:23Z"
    },
    {
      "sku": "6000204264327",
      "status": "not_found",
      "store_id": "1085",
      "store_slug": "lachenaie-terrebonne-qc-1085",
      "checked_at": "2026-02-12T04:16:25Z"
    },
    {
      "sku": "6000207650617",
      "status": "not_found",
      "store_id": "1085",
      "store_slug": "lachenaie-terrebonne-qc-1085",
      "checked_at": "2026-02-12T04:16:26Z"
    }
  ]
}
